soorma_common/__init__.py
soorma_common/a2a.py
soorma_common/events.py
soorma_common/models.py
soorma_common/py.typed
soorma_common/state.py
soorma_common/tracking.py
soorma_common-0.7.5.dist-info/METADATA
soorma_common-0.7.5.dist-info/WHEEL
soorma_common-0.7.5.dist-info/RECORD
