Metadata-Version: 2.4
Name: soorma-common
Version: 0.7.5
Summary: Common models and DTOs for Soorma platform services
License: MIT
Requires-Python: >=3.11
Requires-Dist: pydantic>=2.0.0
Provides-Extra: dev
Requires-Dist: pytest-asyncio>=0.21.0; extra == 'dev'
Requires-Dist: pytest>=7.0.0; extra == 'dev'
